{
  "updated_at": "2026-02-19T02:33:09.636778",
  "sol_price": 81.75,
  "summary": {
    "total_mcap": 1238416.0,
    "total_volume": 68839.79000000001,
    "total_earnings_sol": 6610.212902167999,
    "total_earnings_usd": 540384.904752234,
    "avg_change_24h": -3.9975,
    "active_tokens": 4
  },
  "tokens": [
    {
      "ticker": "$GAS",
      "name": "Gastown",
      "creator": "Steve Yegge",
      "social": "https://x.com/Steve_Yegge",
      "social_handle": "@Steve_Yegge",
      "project_url": "https://github.com/steveyegge/gastown",
      "bags_url": "https://bags.fm/7pskt3A1Zsjhngazam7vHWjWHnfgiRump916Xj7ABAGS",
      "earnings": 2508.114988381,
      "earnings_usd": 205038.40030014675,
      "description": "Multi-agent AI orchestrator; royalties fund ongoing development of complex agent systems.",
      "price": 6.304e-05,
      "fdv": 63033.0,
      "volume_24h": 5057.29,
      "liquidity": 17364.72,
      "change_5m": 0.0,
      "change_1h": -4.71,
      "change_6h": 2.09,
      "change_24h": 1.88,
      "pair_age": "1m 13d",
      "url": "https://dexscreener.com/solana/finu5nsfwvjqbafdesxdxvlhqja3h7qybrluqfrb27v9",
      "pair_address": "FiNu5nSFwvjQbAFDESxDxvLhQJa3H7QYBrLUqFRB27v9",
      "active": true,
      "github_stars": 9725,
      "github_forks": 751,
      "github_watchers": 9725,
      "github_language": "Go",
      "github_contributors": 4440,
      "github_recent_commits": 42870,
      "github_open_issues": 74,
      "github_open_prs": 270,
      "reddit_mentions": 0,
      "hn_mentions": 67,
      "twitter_followers": 28200,
      "twitter_source": "creator_profile",
      "twitter_official": true
    },
    {
      "ticker": "$RALPH",
      "name": "Ralph Wiggum Technique",
      "creator": "Geoffrey Huntley",
      "social": "https://x.com/geoffreyhuntley",
      "social_handle": "@geoffreyhuntley",
      "project_url": "https://github.com/ghuntley/how-to-ralph-wiggum",
      "bags_url": "https://bags.fm/CxWPdDBqxVo3fnTMRTvNuSrd4gkp78udSrFvkVDBAGS",
      "earnings": 2387.402130098,
      "earnings_usd": 195170.1241355115,
      "description": "Autonomous AI coding loops; royalties support open AI research and esoteric experiments.",
      "price": 0.0001664,
      "fdv": 166446.0,
      "volume_24h": 12982.68,
      "liquidity": 28127.03,
      "change_5m": -0.15,
      "change_1h": 1.39,
      "change_6h": 0.71,
      "change_24h": 4.14,
      "pair_age": "1m 14d",
      "url": "https://dexscreener.com/solana/dbyk8geixwneh2zfw2lo1svuq1wkhaeqyndsrakq6bhf",
      "pair_address": "DbyK8gEiXwNeh2zFW2Lo1svUQ1WkHAeQyNDsRaKQ6BHf",
      "active": true,
      "github_stars": 1308,
      "github_forks": 125,
      "github_watchers": 1308,
      "github_language": "HTML",
      "github_contributors": 1,
      "github_recent_commits": 0,
      "github_open_issues": 1,
      "github_open_prs": 1,
      "reddit_mentions": 0,
      "hn_mentions": 1,
      "twitter_followers": 72400,
      "twitter_source": "creator_profile",
      "twitter_official": true
    },
    {
      "ticker": "$GSD",
      "name": "Get Shit Done",
      "creator": "Lex Christopherson",
      "social": "https://x.com/official_taches",
      "social_handle": "@official_taches",
      "project_url": "https://github.com/glittercowboy/get-shit-done",
      "bags_url": "https://bags.fm/8116V1BW9zaXUM6pVhWVaAduKrLcEBi3RGXedKTrBAGS",
      "earnings": 1186.776872306,
      "earnings_usd": 97019.00931101551,
      "description": "Vibe-coding automation tool; royalties provide risk-free OSS maintenance funding.",
      "price": 0.0009544,
      "fdv": 954419.0,
      "volume_24h": 49345.86,
      "liquidity": 76009.96,
      "change_5m": 0.0,
      "change_1h": 3.36,
      "change_6h": -9.2,
      "change_24h": -4.85,
      "pair_age": "1m 3d",
      "url": "https://dexscreener.com/solana/dwudwjvan7bzkw9zwlbyv6kspdlvhwzrqy6ebk8xzxkv",
      "pair_address": "DwudWjVAN7bZkW9zWLbYv6ksPdLvHWZRqy6eBk8xZXKV",
      "active": true,
      "github_stars": 15834,
      "github_forks": 1453,
      "github_watchers": 15834,
      "github_language": "JavaScript",
      "github_contributors": 870,
      "github_recent_commits": 7680,
      "github_open_issues": 162,
      "github_open_prs": 2940,
      "reddit_mentions": 0,
      "hn_mentions": 18,
      "twitter_followers": 764,
      "twitter_source": "creator_profile",
      "twitter_official": true
    },
    {
      "ticker": "$LEON",
      "name": "LEON AI",
      "creator": "Louis Grenard",
      "social": "https://x.com/grenlouis",
      "social_handle": "@grenlouis",
      "project_url": "https://github.com/leon-ai/leon",
      "bags_url": "https://bags.fm/Fnmq5udTPPkxGjw8nDtnRsjJWfHfdNmsfKGLhUerBAGS",
      "earnings": 527.918911383,
      "earnings_usd": 43157.37100556025,
      "description": "Open-source personal assistant; royalties support ongoing AI development.",
      "price": 5.452e-05,
      "fdv": 54518.0,
      "volume_24h": 1453.96,
      "liquidity": 16086.54,
      "change_5m": 0.0,
      "change_1h": 0.18,
      "change_6h": -6.67,
      "change_24h": -17.16,
      "pair_age": "1m 6d",
      "url": "https://dexscreener.com/solana/gzupt46aogt2j3hfziba4biknx1k4f525b9hastbgla7",
      "pair_address": "GZUPT46aogt2j3HFZiBa4bikNx1K4f525B9hAsTBGLA7",
      "active": true,
      "github_stars": 16994,
      "github_forks": 1422,
      "github_watchers": 16994,
      "github_language": "TypeScript",
      "github_contributors": 690,
      "github_recent_commits": 1170,
      "github_open_issues": 103,
      "github_open_prs": 390,
      "reddit_mentions": 0,
      "hn_mentions": 770,
      "twitter_followers": 1733,
      "twitter_source": "creator_profile",
      "twitter_official": true
    }
  ]
}