{
  "updated_at": "2026-01-27T16:35:20.435242",
  "sol_price": 126.06,
  "summary": {
    "total_mcap": 2411579.0,
    "total_volume": 650958.5599999999,
    "total_earnings_sol": 5880.765000734001,
    "total_earnings_usd": 741329.235992528,
    "avg_change_24h": -30.5775,
    "active_tokens": 4
  },
  "tokens": [
    {
      "ticker": "$GAS",
      "name": "Gastown",
      "creator": "Steve Yegge",
      "social": "https://x.com/Steve_Yegge",
      "social_handle": "@Steve_Yegge",
      "project_url": "https://github.com/steveyegge/gastown",
      "bags_url": "https://bags.fm/7pskt3A1Zsjhngazam7vHWjWHnfgiRump916Xj7ABAGS",
      "earnings": 2437.054077342,
      "earnings_usd": 307215.0369897325,
      "description": "Multi-agent AI orchestrator; royalties fund ongoing development of complex agent systems.",
      "price": 0.0002037,
      "fdv": 203678.0,
      "volume_24h": 42635.1,
      "liquidity": 38873.29,
      "change_5m": 0.07,
      "change_1h": -3.42,
      "change_6h": -15.73,
      "change_24h": -14.3,
      "pair_age": "21d",
      "url": "https://dexscreener.com/solana/finu5nsfwvjqbafdesxdxvlhqja3h7qybrluqfrb27v9",
      "pair_address": "FiNu5nSFwvjQbAFDESxDxvLhQJa3H7QYBrLUqFRB27v9",
      "active": true,
      "github_stars": 6260,
      "github_forks": 527,
      "github_watchers": 6260,
      "github_language": "Go",
      "github_contributors": 2850,
      "github_recent_commits": 43500,
      "github_open_issues": 306,
      "github_open_prs": 4530,
      "reddit_mentions": 0,
      "hn_mentions": 61,
      "twitter_followers": 28200,
      "twitter_source": "creator_profile",
      "twitter_official": true
    },
    {
      "ticker": "$RALPH",
      "name": "Ralph Wiggum Technique",
      "creator": "Geoffrey Huntley",
      "social": "https://x.com/geoffreyhuntley",
      "social_handle": "@geoffreyhuntley",
      "project_url": "https://github.com/ghuntley/how-to-ralph-wiggum",
      "bags_url": "https://bags.fm/CxWPdDBqxVo3fnTMRTvNuSrd4gkp78udSrFvkVDBAGS",
      "earnings": 2188.982852785,
      "earnings_usd": 275943.1784220771,
      "description": "Autonomous AI coding loops; royalties support open AI research and esoteric experiments.",
      "price": 0.000439,
      "fdv": 439055.0,
      "volume_24h": 194203.48,
      "liquidity": 59486.16,
      "change_5m": 0.93,
      "change_1h": -4.18,
      "change_6h": -8.68,
      "change_24h": -14.46,
      "pair_age": "22d",
      "url": "https://dexscreener.com/solana/dbyk8geixwneh2zfw2lo1svuq1wkhaeqyndsrakq6bhf",
      "pair_address": "DbyK8gEiXwNeh2zFW2Lo1svUQ1WkHAeQyNDsRaKQ6BHf",
      "active": true,
      "github_stars": 1096,
      "github_forks": 106,
      "github_watchers": 1096,
      "github_language": "HTML",
      "github_contributors": 1,
      "github_recent_commits": 630,
      "github_open_issues": 1,
      "github_open_prs": 1,
      "reddit_mentions": 0,
      "hn_mentions": 1,
      "twitter_followers": 72400,
      "twitter_source": "creator_profile",
      "twitter_official": true
    },
    {
      "ticker": "$GSD",
      "name": "Get Shit Done",
      "creator": "Lex Christopherson",
      "social": "https://x.com/official_taches",
      "social_handle": "@official_taches",
      "project_url": "https://github.com/glittercowboy/get-shit-done",
      "bags_url": "https://bags.fm/8116V1BW9zaXUM6pVhWVaAduKrLcEBi3RGXedKTrBAGS",
      "earnings": 761.216935909,
      "earnings_usd": 95959.00694068855,
      "description": "Vibe-coding automation tool; royalties provide risk-free OSS maintenance funding.",
      "price": 0.001663,
      "fdv": 1663875.0,
      "volume_24h": 370817.91,
      "liquidity": 111908.27,
      "change_5m": -1.06,
      "change_1h": -12.1,
      "change_6h": -22.3,
      "change_24h": -51.24,
      "pair_age": "10d",
      "url": "https://dexscreener.com/solana/dwudwjvan7bzkw9zwlbyv6kspdlvhwzrqy6ebk8xzxkv",
      "pair_address": "DwudWjVAN7bZkW9zWLbYv6ksPdLvHWZRqy6eBk8xZXKV",
      "active": true,
      "github_stars": 8498,
      "github_forks": 846,
      "github_watchers": 8498,
      "github_language": "JavaScript",
      "github_contributors": 300,
      "github_recent_commits": 17400,
      "github_open_issues": 162,
      "github_open_prs": 1530,
      "reddit_mentions": 0,
      "hn_mentions": 14,
      "twitter_followers": 764,
      "twitter_source": "creator_profile",
      "twitter_official": true
    },
    {
      "ticker": "$LEON",
      "name": "LEON AI",
      "creator": "Louis Grenard",
      "social": "https://x.com/grenlouis",
      "social_handle": "@grenlouis",
      "project_url": "https://github.com/leon-ai/leon",
      "bags_url": "https://bags.fm/Fnmq5udTPPkxGjw8nDtnRsjJWfHfdNmsfKGLhUerBAGS",
      "earnings": 493.511134698,
      "earnings_usd": 62212.01364002988,
      "description": "Open-source personal assistant; royalties support ongoing AI development.",
      "price": 0.0001049,
      "fdv": 104971.0,
      "volume_24h": 43302.07,
      "liquidity": 27695.59,
      "change_5m": -4.21,
      "change_1h": -7.62,
      "change_6h": -29.89,
      "change_24h": -42.31,
      "pair_age": "13d",
      "url": "https://dexscreener.com/solana/gzupt46aogt2j3hfziba4biknx1k4f525b9hastbgla7",
      "pair_address": "GZUPT46aogt2j3HFZiBa4bikNx1K4f525B9hAsTBGLA7",
      "active": true,
      "github_stars": 16934,
      "github_forks": 1418,
      "github_watchers": 16934,
      "github_language": "TypeScript",
      "github_contributors": 660,
      "github_recent_commits": 780,
      "github_open_issues": 103,
      "github_open_prs": 390,
      "reddit_mentions": 0,
      "hn_mentions": 732,
      "twitter_followers": 1733,
      "twitter_source": "creator_profile",
      "twitter_official": true
    }
  ]
}